Workbook

Sheet Dashboard
A1: 💰 CONTROLE FINANCEIRO — WILL & SÁ | P1: =SUMIFS(Lancamentos!$G:$G,Lancamentos!$B:$B,">="&DATE($E$2,$B$2,1),Lancamentos!$B:$B,"<="&DATE($E$2,$B$2+1,0),Lancamentos!$A:$A,"Receita",Lancamentos!$F:$F,1) | Q1: =SUMIFS(Lancamentos!$G:$G,Lancamentos!$B:$B,">="&DATE($E$2,$B$2,1),Lancamentos!$B:$B,"<="&DATE($E$2,$B$2+1,0),Lancamentos!$A:$A,"Receita",Lancamentos!$F:$F,2) | R1: =SUMIFS(Lancamentos!$G:$G,Lancamentos!$B:$B,">="&DATE($E$2,$B$2,1),Lancamentos!$B:$B,"<="&DATE($E$2,$B$2+1,0),Lancamentos!$A:$A,"Despesa",Lancamentos!$F:$F,1)
A2: MÊS | B2: 7 | D2: ANO | E2: 2026 | F2: MODO | G2: C1+C2 | H2: =TEXT(DATE(E2,B2,1),"MMMM / YYYY")&" | Modo: "&G2 | P2: =SUMIFS(Lancamentos!$G:$G,Lancamentos!$B:$B,">="&DATE($E$2,$B$2,1),Lancamentos!$B:$B,"<="&DATE($E$2,$B$2+1,0),Lancamentos!$A:$A,"Despesa",Lancamentos!$F:$F,2)
B3: =B2 | D3: =E2
A4: =IF(G2="C1","⏱ CICLO 1 — Lançamentos de 1 a 14",IF(G2="C2","📦 CICLO 2 — Lançamentos do dia 15 ao fim do mês","📆 MÊS COMPLETO — Ciclo 1 (dias 1-14) + Ciclo 2 (dias 15-fim)"))
A5: 📥 Receitas | B5: =CHOOSE(MATCH($G$2,{"C1","C2","C1+C2"},0),SUMIFS(Lancamentos!$G:$G,Lancamentos!$B:$B,">="&DATE($E$2,$B$2,1),Lancamentos!$B:$B,"<="&DATE($E$2,$B$2+1,0),Lancamentos!$A:$A,"Receita",Lancamentos!$F:$F,1),SUMIFS(Lancamentos!$G:$G,Lancamentos!$B:$B,">="&DATE($E$2,$B$2,1),Lancamentos!$B:$B,"<="&DATE($E$2,$B$2+1,0),Lancamentos!$A:$A,"Receita",Lancamentos!$F:$F,2),SUMIFS(Lancamentos!$G:$G,Lancamentos!$B:$B,">="&DATE($E$2,$B$2,1),Lancamentos!$B:$B,"<="&DATE($E$2,$B$2+1,0),Lancamentos!$A:$A,"Receita"))
A6: 📤 Despesas | B6: =CHOOSE(MATCH($G$2,{"C1","C2","C1+C2"},0),SUMIFS(Lancamentos!$G:$G,Lancamentos!$B:$B,">="&DATE($E$2,$B$2,1),Lancamentos!$B:$B,"<="&DATE($E$2,$B$2+1,0),Lancamentos!$A:$A,"Despesa",Lancamentos!$F:$F,1),SUMIFS(Lancamentos!$G:$G,Lancamentos!$B:$B,">="&DATE($E$2,$B$2,1),Lancamentos!$B:$B,"<="&DATE($E$2,$B$2+1,0),Lancamentos!$A:$A,"Despesa",Lancamentos!$F:$F,2),SUMIFS(Lancamentos!$G:$G,Lancamentos!$B:$B,">="&DATE($E$2,$B$2,1),Lancamentos!$B:$B,"<="&DATE($E$2,$B$2+1,0),Lancamentos!$A:$A,"Despesa"))
A7: 📊 % Comprometido | B7: =IF(B5=0,"—",TEXT(B6/B5,"0%")&" da receita")
A9: =IF(B5-B6>=0,"💰 SALDO ▲","💰 SALDO ▼") | C9: =B5-B6 | G9: =IF(B5-B6>=0,"✅ Sobrou "&TEXT(ABS(B5-B6),"#,##0.00")&" neste período","⚠️ Déficit de "&TEXT(ABS(B5-B6),"#,##0.00"))
A10: 🔵 A Receber | B10: =CHOOSE(MATCH($G$2,{"C1","C2","C1+C2"},0),SUMIFS(Lancamentos!$G:$G,Lancamentos!$B:$B,">="&DATE($E$2,$B$2,1),Lancamentos!$B:$B,"<="&DATE($E$2,$B$2+1,0),Lancamentos!$A:$A,"Receita",Lancamentos!$F:$F,1,Lancamentos!$H:$H,"A Receber"),SUMIFS(Lancamentos!$G:$G,Lancamentos!$B:$B,">="&DATE($E$2,$B$2,1),Lancamentos!$B:$B,"<="&DATE($E$2,$B$2+1,0),Lancamentos!$A:$A,"Receita",Lancamentos!$F:$F,2,Lancamentos!$H:$H,"A Receber"),SUMIFS(Lancamentos!$G:$G,Lancamentos!$B:$B,">="&DATE($E$2,$B$2,1),Lancamentos!$B:$B,"<="&DATE($E$2,$B$2+1,0),Lancamentos!$A:$A,"Receita",Lancamentos!$H:$H,"A Receber"))
A11: 🔴 A Pagar | B11: =CHOOSE(MATCH($G$2,{"C1","C2","C1+C2"},0),SUMIFS(Lancamentos!$G:$G,Lancamentos!$B:$B,">="&DATE($E$2,$B$2,1),Lancamentos!$B:$B,"<="&DATE($E$2,$B$2+1,0),Lancamentos!$A:$A,"Despesa",Lancamentos!$F:$F,1,Lancamentos!$H:$H,"A Pagar"),SUMIFS(Lancamentos!$G:$G,Lancamentos!$B:$B,">="&DATE($E$2,$B$2,1),Lancamentos!$B:$B,"<="&DATE($E$2,$B$2+1,0),Lancamentos!$A:$A,"Despesa",Lancamentos!$F:$F,2,Lancamentos!$H:$H,"A Pagar"),SUMIFS(Lancamentos!$G:$G,Lancamentos!$B:$B,">="&DATE($E$2,$B$2,1),Lancamentos!$B:$B,"<="&DATE($E$2,$B$2+1,0),Lancamentos!$A:$A,"Despesa",Lancamentos!$H:$H,"A Pagar"))
A13: 📊 GASTOS POR CATEGORIA
A14: Categoria | B14: Valor (R$) | E14: Categoria | F14: Valor (R$) | H14: Categoria | I14: Valor (R$)
A15: Aluguel | B15: =CHOOSE(MATCH($G$2,{"C1","C2","C1+C2"},0),SUMIFS(Lancamentos!$G:$G,Lancamentos!$B:$B,">="&DATE($E$2,$B$2,1),Lancamentos!$B:$B,"<="&DATE($E$2,$B$2+1,0),Lancamentos!$A:$A,"Despesa",Lancamentos!$F:$F,1,Lancamentos!$D:$D,A15),SUMIFS(Lancamentos!$G:$G,Lancamentos!$B:$B,">="&DATE($E$2,$B$2,1),Lancamentos!$B:$B,"<="&DATE($E$2,$B$2+1,0),Lancamentos!$A:$A,"Despesa",Lancamentos!$F:$F,2,Lancamentos!$D:$D,A15),SUMIFS(Lancamentos!$G:$G,Lancamentos!$B:$B,">="&DATE($E$2,$B$2,1),Lancamentos!$B:$B,"<="&DATE($E$2,$B$2+1,0),Lancamentos!$A:$A,"Despesa",Lancamentos!$D:$D,A15)) | E15: Lazer | F15: =CHOOSE(MATCH($G$2,{"C1","C2","C1+C2"},0),SUMIFS(Lancamentos!$G:$G,Lancamentos!$B:$B,">="&DATE($E$2,$B$2,1),Lancamentos!$B:$B,"<="&DATE($E$2,$B$2+1,0),Lancamentos!$A:$A,"Despesa",Lancamentos!$F:$F,1,Lancamentos!$D:$D,E15),SUMIFS(Lancamentos!$G:$G,Lancamentos!$B:$B,">="&DATE($E$2,$B$2,1),Lancamentos!$B:$B,"<="&DATE($E$2,$B$2+1,0),Lancamentos!$A:$A,"Despesa",Lancamentos!$F:$F,2,Lancamentos!$D:$D,E15),SUMIFS(Lancamentos!$G:$G,Lancamentos!$B:$B,">="&DATE($E$2,$B$2,1),Lancamentos!$B:$B,"<="&DATE($E$2,$B$2+1,0),Lancamentos!$A:$A,"Despesa",Lancamentos!$D:$D,E15))
A16: Alimentação | B16: =CHOOSE(MATCH($G$2,{"C1","C2","C1+C2"},0),SUMIFS(Lancamentos!$G:$G,Lancamentos!$B:$B,">="&DATE($E$2,$B$2,1),Lancamentos!$B:$B,"<="&DATE($E$2,$B$2+1,0),Lancamentos!$A:$A,"Despesa",Lancamentos!$F:$F,1,Lancamentos!$D:$D,A16),SUMIFS(Lancamentos!$G:$G,Lancamentos!$B:$B,">="&DATE($E$2,$B$2,1),Lancamentos!$B:$B,"<="&DATE($E$2,$B$2+1,0),Lancamentos!$A:$A,"Despesa",Lancamentos!$F:$F,2,Lancamentos!$D:$D,A16),SUMIFS(Lancamentos!$G:$G,Lancamentos!$B:$B,">="&DATE($E$2,$B$2,1),Lancamentos!$B:$B,"<="&DATE($E$2,$B$2+1,0),Lancamentos!$A:$A,"Despesa",Lancamentos!$D:$D,A16)) | E16: Cartões | F16: =CHOOSE(MATCH($G$2,{"C1","C2","C1+C2"},0),SUMIFS(Lancamentos!$G:$G,Lancamentos!$B:$B,">="&DATE($E$2,$B$2,1),Lancamentos!$B:$B,"<="&DATE($E$2,$B$2+1,0),Lancamentos!$A:$A,"Despesa",Lancamentos!$F:$F,1,Lancamentos!$D:$D,E16),SUMIFS(Lancamentos!$G:$G,Lancamentos!$B:$B,">="&DATE($E$2,$B$2,1),Lancamentos!$B:$B,"<="&DATE($E$2,$B$2+1,0),Lancamentos!$A:$A,"Despesa",Lancamentos!$F:$F,2,Lancamentos!$D:$D,E16),SUMIFS(Lancamentos!$G:$G,Lancamentos!$B:$B,">="&DATE($E$2,$B$2,1),Lancamentos!$B:$B,"<="&DATE($E$2,$B$2+1,0),Lancamentos!$A:$A,"Despesa",Lancamentos!$D:$D,E16))
A17: Transporte | B17: =CHOOSE(MATCH($G$2,{"C1","C2","C1+C2"},0),SUMIFS(Lancamentos!$G:$G,Lancamentos!$B:$B,">="&DATE($E$2,$B$2,1),Lancamentos!$B:$B,"<="&DATE($E$2,$B$2+1,0),Lancamentos!$A:$A,"Despesa",Lancamentos!$F:$F,1,Lancamentos!$D:$D,A17),SUMIFS(Lancamentos!$G:$G,Lancamentos!$B:$B,">="&DATE($E$2,$B$2,1),Lancamentos!$B:$B,"<="&DATE($E$2,$B$2+1,0),Lancamentos!$A:$A,"Despesa",Lancamentos!$F:$F,2,Lancamentos!$D:$D,A17),SUMIFS(Lancamentos!$G:$G,Lancamentos!$B:$B,">="&DATE($E$2,$B$2,1),Lancamentos!$B:$B,"<="&DATE($E$2,$B$2+1,0),Lancamentos!$A:$A,"Despesa",Lancamentos!$D:$D,A17)) | E17: Celular | F17: =CHOOSE(MATCH($G$2,{"C1","C2","C1+C2"},0),SUMIFS(Lancamentos!$G:$G,Lancamentos!$B:$B,">="&DATE($E$2,$B$2,1),Lancamentos!$B:$B,"<="&DATE($E$2,$B$2+1,0),Lancamentos!$A:$A,"Despesa",Lancamentos!$F:$F,1,Lancamentos!$D:$D,E17),SUMIFS(Lancamentos!$G:$G,Lancamentos!$B:$B,">="&DATE($E$2,$B$2,1),Lancamentos!$B:$B,"<="&DATE($E$2,$B$2+1,0),Lancamentos!$A:$A,"Despesa",Lancamentos!$F:$F,2,Lancamentos!$D:$D,E17),SUMIFS(Lancamentos!$G:$G,Lancamentos!$B:$B,">="&DATE($E$2,$B$2,1),Lancamentos!$B:$B,"<="&DATE($E$2,$B$2+1,0),Lancamentos!$A:$A,"Despesa",Lancamentos!$D:$D,E17))
A18: Saúde | B18: =CHOOSE(MATCH($G$2,{"C1","C2","C1+C2"},0),SUMIFS(Lancamentos!$G:$G,Lancamentos!$B:$B,">="&DATE($E$2,$B$2,1),Lancamentos!$B:$B,"<="&DATE($E$2,$B$2+1,0),Lancamentos!$A:$A,"Despesa",Lancamentos!$F:$F,1,Lancamentos!$D:$D,A18),SUMIFS(Lancamentos!$G:$G,Lancamentos!$B:$B,">="&DATE($E$2,$B$2,1),Lancamentos!$B:$B,"<="&DATE($E$2,$B$2+1,0),Lancamentos!$A:$A,"Despesa",Lancamentos!$F:$F,2,Lancamentos!$D:$D,A18),SUMIFS(Lancamentos!$G:$G,Lancamentos!$B:$B,">="&DATE($E$2,$B$2,1),Lancamentos!$B:$B,"<="&DATE($E$2,$B$2+1,0),Lancamentos!$A:$A,"Despesa",Lancamentos!$D:$D,A18)) | E18: Outros | F18: =CHOOSE(MATCH($G$2,{"C1","C2","C1+C2"},0),SUMIFS(Lancamentos!$G:$G,Lancamentos!$B:$B,">="&DATE($E$2,$B$2,1),Lancamentos!$B:$B,"<="&DATE($E$2,$B$2+1,0),Lancamentos!$A:$A,"Despesa",Lancamentos!$F:$F,1,Lancamentos!$D:$D,E18),SUMIFS(Lancamentos!$G:$G,Lancamentos!$B:$B,">="&DATE($E$2,$B$2,1),Lancamentos!$B:$B,"<="&DATE($E$2,$B$2+1,0),Lancamentos!$A:$A,"Despesa",Lancamentos!$F:$F,2,Lancamentos!$D:$D,E18),SUMIFS(Lancamentos!$G:$G,Lancamentos!$B:$B,">="&DATE($E$2,$B$2,1),Lancamentos!$B:$B,"<="&DATE($E$2,$B$2+1,0),Lancamentos!$A:$A,"Despesa",Lancamentos!$D:$D,E18))

Sheet Resumo Anual
A1: 📅 RESUMO ANUAL
A2: ANO | B2: =Dashboard!E2
A4: Mês | B4: Receitas | C4: Despesas | D4: Saldo | E4: % Gasto | F4: Rec C1 (1-14) | G4: Rec C2 (15-fim) | H4: Desp C1 (1-14)
A5: Janeiro | B5: =SUMIFS(Lancamentos!$G:$G,Lancamentos!$A:$A,"Receita",Lancamentos!$B:$B,">="&DATE($B$2,1,1),Lancamentos!$B:$B,"<="&DATE($B$2,1+1,0)) | C5: =SUMIFS(Lancamentos!$G:$G,Lancamentos!$A:$A,"Despesa",Lancamentos!$B:$B,">="&DATE($B$2,1,1),Lancamentos!$B:$B,"<="&DATE($B$2,1+1,0)) | D5: =B5-C5 | E5: =IF(B5=0,0,C5/B5) | F5: =SUMIFS(Lancamentos!$G:$G,Lancamentos!$A:$A,"Receita",Lancamentos!$B:$B,">="&DATE($B$2,1,1),Lancamentos!$B:$B,"<="&DATE($B$2,1+1,0),Lancamentos!$F:$F,1) | G5: =SUMIFS(Lancamentos!$G:$G,Lancamentos!$A:$A,"Receita",Lancamentos!$B:$B,">="&DATE($B$2,1,1),Lancamentos!$B:$B,"<="&DATE($B$2,1+1,0),Lancamentos!$F:$F,2) | H5: =SUMIFS(Lancamentos!$G:$G,Lancamentos!$A:$A,"Despesa",Lancamentos!$B:$B,">="&DATE($B$2,1,1),Lancamentos!$B:$B,"<="&DATE($B$2,1+1,0),Lancamentos!$F:$F,1)
A6: Fevereiro | B6: =SUMIFS(Lancamentos!$G:$G,Lancamentos!$A:$A,"Receita",Lancamentos!$B:$B,">="&DATE($B$2,2,1),Lancamentos!$B:$B,"<="&DATE($B$2,2+1,0)) | C6: =SUMIFS(Lancamentos!$G:$G,Lancamentos!$A:$A,"Despesa",Lancamentos!$B:$B,">="&DATE($B$2,2,1),Lancamentos!$B:$B,"<="&DATE($B$2,2+1,0)) | D6: =B6-C6 | E6: =IF(B6=0,0,C6/B6) | F6: =SUMIFS(Lancamentos!$G:$G,Lancamentos!$A:$A,"Receita",Lancamentos!$B:$B,">="&DATE($B$2,2,1),Lancamentos!$B:$B,"<="&DATE($B$2,2+1,0),Lancamentos!$F:$F,1) | G6: =SUMIFS(Lancamentos!$G:$G,Lancamentos!$A:$A,"Receita",Lancamentos!$B:$B,">="&DATE($B$2,2,1),Lancamentos!$B:$B,"<="&DATE($B$2,2+1,0),Lancamentos!$F:$F,2) | H6: =SUMIFS(Lancamentos!$G:$G,Lancamentos!$A:$A,"Despesa",Lancamentos!$B:$B,">="&DATE($B$2,2,1),Lancamentos!$B:$B,"<="&DATE($B$2,2+1,0),Lancamentos!$F:$F,1)
A7: Março | B7: =SUMIFS(Lancamentos!$G:$G,Lancamentos!$A:$A,"Receita",Lancamentos!$B:$B,">="&DATE($B$2,3,1),Lancamentos!$B:$B,"<="&DATE($B$2,3+1,0)) | C7: =SUMIFS(Lancamentos!$G:$G,Lancamentos!$A:$A,"Despesa",Lancamentos!$B:$B,">="&DATE($B$2,3,1),Lancamentos!$B:$B,"<="&DATE($B$2,3+1,0)) | D7: =B7-C7 | E7: =IF(B7=0,0,C7/B7) | F7: =SUMIFS(Lancamentos!$G:$G,Lancamentos!$A:$A,"Receita",Lancamentos!$B:$B,">="&DATE($B$2,3,1),Lancamentos!$B:$B,"<="&DATE($B$2,3+1,0),Lancamentos!$F:$F,1) | G7: =SUMIFS(Lancamentos!$G:$G,Lancamentos!$A:$A,"Receita",Lancamentos!$B:$B,">="&DATE($B$2,3,1),Lancamentos!$B:$B,"<="&DATE($B$2,3+1,0),Lancamentos!$F:$F,2) | H7: =SUMIFS(Lancamentos!$G:$G,Lancamentos!$A:$A,"Despesa",Lancamentos!$B:$B,">="&DATE($B$2,3,1),Lancamentos!$B:$B,"<="&DATE($B$2,3+1,0),Lancamentos!$F:$F,1)
A8: Abril | B8: =SUMIFS(Lancamentos!$G:$G,Lancamentos!$A:$A,"Receita",Lancamentos!$B:$B,">="&DATE($B$2,4,1),Lancamentos!$B:$B,"<="&DATE($B$2,4+1,0)) | C8: =SUMIFS(Lancamentos!$G:$G,Lancamentos!$A:$A,"Despesa",Lancamentos!$B:$B,">="&DATE($B$2,4,1),Lancamentos!$B:$B,"<="&DATE($B$2,4+1,0)) | D8: =B8-C8 | E8: =IF(B8=0,0,C8/B8) | F8: =SUMIFS(Lancamentos!$G:$G,Lancamentos!$A:$A,"Receita",Lancamentos!$B:$B,">="&DATE($B$2,4,1),Lancamentos!$B:$B,"<="&DATE($B$2,4+1,0),Lancamentos!$F:$F,1) | G8: =SUMIFS(Lancamentos!$G:$G,Lancamentos!$A:$A,"Receita",Lancamentos!$B:$B,">="&DATE($B$2,4,1),Lancamentos!$B:$B,"<="&DATE($B$2,4+1,0),Lancamentos!$F:$F,2) | H8: =SUMIFS(Lancamentos!$G:$G,Lancamentos!$A:$A,"Despesa",Lancamentos!$B:$B,">="&DATE($B$2,4,1),Lancamentos!$B:$B,"<="&DATE($B$2,4+1,0),Lancamentos!$F:$F,1)
A9: Maio | B9: =SUMIFS(Lancamentos!$G:$G,Lancamentos!$A:$A,"Receita",Lancamentos!$B:$B,">="&DATE($B$2,5,1),Lancamentos!$B:$B,"<="&DATE($B$2,5+1,0)) | C9: =SUMIFS(Lancamentos!$G:$G,Lancamentos!$A:$A,"Despesa",Lancamentos!$B:$B,">="&DATE($B$2,5,1),Lancamentos!$B:$B,"<="&DATE($B$2,5+1,0)) | D9: =B9-C9 | E9: =IF(B9=0,0,C9/B9) | F9: =SUMIFS(Lancamentos!$G:$G,Lancamentos!$A:$A,"Receita",Lancamentos!$B:$B,">="&DATE($B$2,5,1),Lancamentos!$B:$B,"<="&DATE($B$2,5+1,0),Lancamentos!$F:$F,1) | G9: =SUMIFS(Lancamentos!$G:$G,Lancamentos!$A:$A,"Receita",Lancamentos!$B:$B,">="&DATE($B$2,5,1),Lancamentos!$B:$B,"<="&DATE($B$2,5+1,0),Lancamentos!$F:$F,2) | H9: =SUMIFS(Lancamentos!$G:$G,Lancamentos!$A:$A,"Despesa",Lancamentos!$B:$B,">="&DATE($B$2,5,1),Lancamentos!$B:$B,"<="&DATE($B$2,5+1,0),Lancamentos!$F:$F,1)
A10: Junho | B10: =SUMIFS(Lancamentos!$G:$G,Lancamentos!$A:$A,"Receita",Lancamentos!$B:$B,">="&DATE($B$2,6,1),Lancamentos!$B:$B,"<="&DATE($B$2,6+1,0)) | C10: =SUMIFS(Lancamentos!$G:$G,Lancamentos!$A:$A,"Despesa",Lancamentos!$B:$B,">="&DATE($B$2,6,1),Lancamentos!$B:$B,"<="&DATE($B$2,6+1,0)) | D10: =B10-C10 | E10: =IF(B10=0,0,C10/B10) | F10: =SUMIFS(Lancamentos!$G:$G,Lancamentos!$A:$A,"Receita",Lancamentos!$B:$B,">="&DATE($B$2,6,1),Lancamentos!$B:$B,"<="&DATE($B$2,6+1,0),Lancamentos!$F:$F,1) | G10: =SUMIFS(Lancamentos!$G:$G,Lancamentos!$A:$A,"Receita",Lancamentos!$B:$B,">="&DATE($B$2,6,1),Lancamentos!$B:$B,"<="&DATE($B$2,6+1,0),Lancamentos!$F:$F,2) | H10: =SUMIFS(Lancamentos!$G:$G,Lancamentos!$A:$A,"Despesa",Lancamentos!$B:$B,">="&DATE($B$2,6,1),Lancamentos!$B:$B,"<="&DATE($B$2,6+1,0),Lancamentos!$F:$F,1)
A11: Julho | B11: =SUMIFS(Lancamentos!$G:$G,Lancamentos!$A:$A,"Receita",Lancamentos!$B:$B,">="&DATE($B$2,7,1),Lancamentos!$B:$B,"<="&DATE($B$2,7+1,0)) | C11: =SUMIFS(Lancamentos!$G:$G,Lancamentos!$A:$A,"Despesa",Lancamentos!$B:$B,">="&DATE($B$2,7,1),Lancamentos!$B:$B,"<="&DATE($B$2,7+1,0)) | D11: =B11-C11 | E11: =IF(B11=0,0,C11/B11) | F11: =SUMIFS(Lancamentos!$G:$G,Lancamentos!$A:$A,"Receita",Lancamentos!$B:$B,">="&DATE($B$2,7,1),Lancamentos!$B:$B,"<="&DATE($B$2,7+1,0),Lancamentos!$F:$F,1) | G11: =SUMIFS(Lancamentos!$G:$G,Lancamentos!$A:$A,"Receita",Lancamentos!$B:$B,">="&DATE($B$2,7,1),Lancamentos!$B:$B,"<="&DATE($B$2,7+1,0),Lancamentos!$F:$F,2) | H11: =SUMIFS(Lancamentos!$G:$G,Lancamentos!$A:$A,"Despesa",Lancamentos!$B:$B,">="&DATE($B$2,7,1),Lancamentos!$B:$B,"<="&DATE($B$2,7+1,0),Lancamentos!$F:$F,1)
A12: Agosto | B12: =SUMIFS(Lancamentos!$G:$G,Lancamentos!$A:$A,"Receita",Lancamentos!$B:$B,">="&DATE($B$2,8,1),Lancamentos!$B:$B,"<="&DATE($B$2,8+1,0)) | C12: =SUMIFS(Lancamentos!$G:$G,Lancamentos!$A:$A,"Despesa",Lancamentos!$B:$B,">="&DATE($B$2,8,1),Lancamentos!$B:$B,"<="&DATE($B$2,8+1,0)) | D12: =B12-C12 | E12: =IF(B12=0,0,C12/B12) | F12: =SUMIFS(Lancamentos!$G:$G,Lancamentos!$A:$A,"Receita",Lancamentos!$B:$B,">="&DATE($B$2,8,1),Lancamentos!$B:$B,"<="&DATE($B$2,8+1,0),Lancamentos!$F:$F,1) | G12: =SUMIFS(Lancamentos!$G:$G,Lancamentos!$A:$A,"Receita",Lancamentos!$B:$B,">="&DATE($B$2,8,1),Lancamentos!$B:$B,"<="&DATE($B$2,8+1,0),Lancamentos!$F:$F,2) | H12: =SUMIFS(Lancamentos!$G:$G,Lancamentos!$A:$A,"Despesa",Lancamentos!$B:$B,">="&DATE($B$2,8,1),Lancamentos!$B:$B,"<="&DATE($B$2,8+1,0),Lancamentos!$F:$F,1)
A13: Setembro | B13: =SUMIFS(Lancamentos!$G:$G,Lancamentos!$A:$A,"Receita",Lancamentos!$B:$B,">="&DATE($B$2,9,1),Lancamentos!$B:$B,"<="&DATE($B$2,9+1,0)) | C13: =SUMIFS(Lancamentos!$G:$G,Lancamentos!$A:$A,"Despesa",Lancamentos!$B:$B,">="&DATE($B$2,9,1),Lancamentos!$B:$B,"<="&DATE($B$2,9+1,0)) | D13: =B13-C13 | E13: =IF(B13=0,0,C13/B13) | F13: =SUMIFS(Lancamentos!$G:$G,Lancamentos!$A:$A,"Receita",Lancamentos!$B:$B,">="&DATE($B$2,9,1),Lancamentos!$B:$B,"<="&DATE($B$2,9+1,0),Lancamentos!$F:$F,1) | G13: =SUMIFS(Lancamentos!$G:$G,Lancamentos!$A:$A,"Receita",Lancamentos!$B:$B,">="&DATE($B$2,9,1),Lancamentos!$B:$B,"<="&DATE($B$2,9+1,0),Lancamentos!$F:$F,2) | H13: =SUMIFS(Lancamentos!$G:$G,Lancamentos!$A:$A,"Despesa",Lancamentos!$B:$B,">="&DATE($B$2,9,1),Lancamentos!$B:$B,"<="&DATE($B$2,9+1,0),Lancamentos!$F:$F,1)
A14: Outubro | B14: =SUMIFS(Lancamentos!$G:$G,Lancamentos!$A:$A,"Receita",Lancamentos!$B:$B,">="&DATE($B$2,10,1),Lancamentos!$B:$B,"<="&DATE($B$2,10+1,0)) | C14: =SUMIFS(Lancamentos!$G:$G,Lancamentos!$A:$A,"Despesa",Lancamentos!$B:$B,">="&DATE($B$2,10,1),Lancamentos!$B:$B,"<="&DATE($B$2,10+1,0)) | D14: =B14-C14 | E14: =IF(B14=0,0,C14/B14) | F14: =SUMIFS(Lancamentos!$G:$G,Lancamentos!$A:$A,"Receita",Lancamentos!$B:$B,">="&DATE($B$2,10,1),Lancamentos!$B:$B,"<="&DATE($B$2,10+1,0),Lancamentos!$F:$F,1) | G14: =SUMIFS(Lancamentos!$G:$G,Lancamentos!$A:$A,"Receita",Lancamentos!$B:$B,">="&DATE($B$2,10,1),Lancamentos!$B:$B,"<="&DATE($B$2,10+1,0),Lancamentos!$F:$F,2) | H14: =SUMIFS(Lancamentos!$G:$G,Lancamentos!$A:$A,"Despesa",Lancamentos!$B:$B,">="&DATE($B$2,10,1),Lancamentos!$B:$B,"<="&DATE($B$2,10+1,0),Lancamentos!$F:$F,1)
A15: Novembro | B15: =SUMIFS(Lancamentos!$G:$G,Lancamentos!$A:$A,"Receita",Lancamentos!$B:$B,">="&DATE($B$2,11,1),Lancamentos!$B:$B,"<="&DATE($B$2,11+1,0)) | C15: =SUMIFS(Lancamentos!$G:$G,Lancamentos!$A:$A,"Despesa",Lancamentos!$B:$B,">="&DATE($B$2,11,1),Lancamentos!$B:$B,"<="&DATE($B$2,11+1,0)) | D15: =B15-C15 | E15: =IF(B15=0,0,C15/B15) | F15: =SUMIFS(Lancamentos!$G:$G,Lancamentos!$A:$A,"Receita",Lancamentos!$B:$B,">="&DATE($B$2,11,1),Lancamentos!$B:$B,"<="&DATE($B$2,11+1,0),Lancamentos!$F:$F,1) | G15: =SUMIFS(Lancamentos!$G:$G,Lancamentos!$A:$A,"Receita",Lancamentos!$B:$B,">="&DATE($B$2,11,1),Lancamentos!$B:$B,"<="&DATE($B$2,11+1,0),Lancamentos!$F:$F,2) | H15: =SUMIFS(Lancamentos!$G:$G,Lancamentos!$A:$A,"Despesa",Lancamentos!$B:$B,">="&DATE($B$2,11,1),Lancamentos!$B:$B,"<="&DATE($B$2,11+1,0),Lancamentos!$F:$F,1)
A16: Dezembro | B16: =SUMIFS(Lancamentos!$G:$G,Lancamentos!$A:$A,"Receita",Lancamentos!$B:$B,">="&DATE($B$2,12,1),Lancamentos!$B:$B,"<="&DATE($B$2,12+1,0)) | C16: =SUMIFS(Lancamentos!$G:$G,Lancamentos!$A:$A,"Despesa",Lancamentos!$B:$B,">="&DATE($B$2,12,1),Lancamentos!$B:$B,"<="&DATE($B$2,12+1,0)) | D16: =B16-C16 | E16: =IF(B16=0,0,C16/B16) | F16: =SUMIFS(Lancamentos!$G:$G,Lancamentos!$A:$A,"Receita",Lancamentos!$B:$B,">="&DATE($B$2,12,1),Lancamentos!$B:$B,"<="&DATE($B$2,12+1,0),Lancamentos!$F:$F,1) | G16: =SUMIFS(Lancamentos!$G:$G,Lancamentos!$A:$A,"Receita",Lancamentos!$B:$B,">="&DATE($B$2,12,1),Lancamentos!$B:$B,"<="&DATE($B$2,12+1,0),Lancamentos!$F:$F,2) | H16: =SUMIFS(Lancamentos!$G:$G,Lancamentos!$A:$A,"Despesa",Lancamentos!$B:$B,">="&DATE($B$2,12,1),Lancamentos!$B:$B,"<="&DATE($B$2,12+1,0),Lancamentos!$F:$F,1)
A17: 📊 TOTAL | B17: =SUM(B5:B16) | C17: =SUM(C5:C16) | D17: =B17-C17 | E17: =IF(B17=0,0,C17/B17)
A19: Indicadores do Ano
A20: Média Rec/mês | B20: =AVERAGEIF(B5:B16,">0") | C20: Média Desp/mês | D20: =AVERAGEIF(C5:C16,">0") | E20: Melhor saldo | F20: =MAX(D5:D16) | G20: Pior saldo | H20: =MIN(D5:D16)

Sheet Lancamentos
A1: Tipo | B1: Data | C1: Descrição | D1: Categoria | E1: Responsável | F1: Ciclo | G1: Valor | H1: Status
A2: Receita | B2: 46208 | C2: Salário Will | D2: Salário | E2: Will | F2: 1 | G2: 5000 | H2: Recebido
A3: Receita | B3: 46208 | C3: Salário Sá | D3: Salário | E3: Sá | F3: 1 | G3: 3800 | H3: Recebido
A4: Despesa | B4: 46206 | C4: Aluguel | D4: Aluguel | E4: Ambos | F4: 1 | G4: 1800 | H4: Pago
A5: Despesa | B5: 46213 | C5: Internet | D5: Celular | E5: Ambos | F5: 1 | G5: 150 | H5: A Pagar
A6: Despesa | B6: 46218 | C6: Fatura Will | D6: Cartões | E6: Will | F6: 2 | G6: 900 | H6: A Pagar
A7: Receita | B7: 46223 | C7: Renda Extra | D7: Renda Extra | E7: Will | F7: 2 | G7: 500 | H7: A Receber

Sheet Cartoes
A1: 💳 CONTROLE DE CARTÕES
A2: Titular | B2: Cartão | C2: Vencimento | D2: Limite | E2: Fatura Atual | F2: Disponível
A3: Will | B3: Nubank | C3: 5 | D3: 15000 | E3: 0 | F3: =D3-E3
A4: Sá | B4: Itaú | C4: 10 | D4: 8000 | E4: 0 | F4: =D4-E4
A5: Ambos | B5: Inter | C5: 15 | D5: 12000 | E5: 0 | F5: =D5-E5

Sheet Config
A1: ⚙️ CATEGORIAS
A2: Categoria
A3: Salário
A4: Renda Extra
A5: 13° Salário
A6: PLR
A7: Férias
A8: Aluguel
A9: Alimentação
A10: Transporte
A11: Saúde
A12: Lazer
... A18: Outros
